monalysa/.DS_Store
monalysa/.idea/.gitignore
monalysa/.idea/inspectionProfiles/Project_Default.xml
monalysa/.idea/inspectionProfiles/profiles_settings.xml
monalysa/.idea/misc.xml
monalysa/.idea/modules.xml
monalysa/.idea/monalysa.iml
monalysa/.idea/vcs.xml
monalysa/README.md
monalysa/__init__.py
monalysa/experimental.py
monalysa/misc.py
monalysa/movements.py
monalysa/preprocess/__init__.py
monalysa/quality/__init__.py
monalysa/quality/smoothness.py
monalysa/tests/__init__.py
monalysa/tests/test_misc.py
monalysa/tests/test_ulfunc.py
monalysa/todo.md
monalysa/ulfunc/.DS_Store
monalysa/ulfunc/__init__.py
monalysa/ulfunc/measures.py
monalysa/ulfunc/ulint.py
monalysa/ulfunc/uluse.py
monalysa/ulfunc/visualizations.py
monalysa-0.2.1.dist-info/LICENSE
monalysa-0.2.1.dist-info/WHEEL
monalysa-0.2.1.dist-info/METADATA
monalysa-0.2.1.dist-info/RECORD
